{"scrapedAt":"2025-12-08 20:30:06","leagueName":"premier-league","day":"Saturday,","date":"01 Oct 2022,","time":"11:30","homeTeam":"West Ham","awayTeam":"Wolves","mlFirstHalf":[{"bookMakerName":"Betclic.fr","hw":"2.00","d":"3.20","aw":"3.95"},{"bookMakerName":"bwin.fr","hw":"2.05","d":"3.30","aw":"3.75"},{"bookMakerName":"Unibet.fr","hw":"1.93","d":"3.28","aw":"3.75"}],"mlSecondHalf":[{"bookMakerName":"Betclic.fr","hw":"2.00","d":"3.20","aw":"3.95"},{"bookMakerName":"bwin.fr","hw":"2.05","d":"3.30","aw":"3.75"},{"bookMakerName":"Unibet.fr","hw":"1.93","d":"3.28","aw":"3.75"}],"mlFullTime":[{"bookMakerName":"Betclic.fr","hw":"2.00","d":"3.20","aw":"3.95"},{"bookMakerName":"bwin.fr","hw":"2.05","d":"3.30","aw":"3.75"},{"bookMakerName":"Unibet.fr","hw":"1.93","d":"3.28","aw":"3.75"}],"underOver25":[{"bookmakerName":"Betclic.fr","oddsOver":"2.08","oddsUnder":"1.61"},{"bookmakerName":"bwin.fr","oddsOver":"2.10","oddsUnder":"1.66"}],"underOver15":[{"bookmakerName":"Betclic.fr","oddsOver":"1.34","oddsUnder":"2.81"},{"bookmakerName":"bwin.fr","oddsOver":"1.36","oddsUnder":"2.90"}],"underOver35":[{"bookmakerName":"Betclic.fr","oddsOver":"3.57","oddsUnder":"1.22"},{"bookmakerName":"bwin.fr","oddsOver":"3.70","oddsUnder":"1.25"}]}