{"scrapedAt":"2025-12-08 21:05:32","leagueName":"premier-league","day":"Sunday,","date":"03 Dec 2023,","time":"06:00","homeTeam":"Bournemouth","awayTeam":"Aston Villa","mlFirstHalf":[{"bookMakerName":"Betclic.fr","hw":"3.05","d":"3.90","aw":"2.02"},{"bookMakerName":"bwin.fr","hw":"2.95","d":"3.60","aw":"2.05"},{"bookMakerName":"Unibet.fr","hw":"3.05","d":"3.82","aw":"2.04"}],"mlSecondHalf":[{"bookMakerName":"Betclic.fr","hw":"3.05","d":"3.90","aw":"2.02"},{"bookMakerName":"bwin.fr","hw":"2.95","d":"3.60","aw":"2.05"},{"bookMakerName":"Unibet.fr","hw":"3.05","d":"3.82","aw":"2.04"}],"mlFullTime":[{"bookMakerName":"Betclic.fr","hw":"3.05","d":"3.90","aw":"2.02"},{"bookMakerName":"bwin.fr","hw":"2.95","d":"3.60","aw":"2.05"},{"bookMakerName":"Unibet.fr","hw":"3.05","d":"3.82","aw":"2.04"}],"underOver25":[{"bookmakerName":"Betclic.fr","oddsOver":"1.42","oddsUnder":"2.40"},{"bookmakerName":"bwin.fr","oddsOver":"1.41","oddsUnder":"2.30"}],"underOver15":[{"bookmakerName":"Betclic.fr","oddsOver":"1.12","oddsUnder":"4.80"},{"bookmakerName":"bwin.fr","oddsOver":"1.12","oddsUnder":"4.40"}],"underOver35":[{"bookmakerName":"Betclic.fr","oddsOver":"2.05","oddsUnder":"1.58"},{"bookmakerName":"bwin.fr","oddsOver":"2.00","oddsUnder":"1.55"}]}