{"scrapedAt":"2025-12-08 21:11:56","leagueName":"premier-league","day":"Saturday,","date":"04 Nov 2023,","time":"08:00","homeTeam":"Sheffield Utd","awayTeam":"Wolves","mlFirstHalf":[{"bookMakerName":"Betclic.fr","hw":"3.87","d":"3.60","aw":"1.78"},{"bookMakerName":"bwin.fr","hw":"3.90","d":"3.50","aw":"1.80"},{"bookMakerName":"Unibet.fr","hw":"4.10","d":"3.62","aw":"1.79"}],"mlSecondHalf":[{"bookMakerName":"Betclic.fr","hw":"3.87","d":"3.60","aw":"1.78"},{"bookMakerName":"bwin.fr","hw":"3.90","d":"3.50","aw":"1.80"},{"bookMakerName":"Unibet.fr","hw":"4.10","d":"3.62","aw":"1.79"}],"mlFullTime":[{"bookMakerName":"Betclic.fr","hw":"3.87","d":"3.60","aw":"1.78"},{"bookMakerName":"bwin.fr","hw":"3.90","d":"3.50","aw":"1.80"},{"bookMakerName":"Unibet.fr","hw":"4.10","d":"3.62","aw":"1.79"}],"underOver25":[{"bookmakerName":"Betclic.fr","oddsOver":"1.72","oddsUnder":"1.80"},{"bookmakerName":"bwin.fr","oddsOver":"1.75","oddsUnder":"1.75"}],"underOver15":[{"bookmakerName":"Betclic.fr","oddsOver":"1.22","oddsUnder":"3.20"},{"bookmakerName":"bwin.fr","oddsOver":"1.24","oddsUnder":"3.10"}],"underOver35":[{"bookmakerName":"Betclic.fr","oddsOver":"2.70","oddsUnder":"1.30"},{"bookmakerName":"bwin.fr","oddsOver":"2.85","oddsUnder":"1.28"}]}