{"scrapedAt":"2025-12-08 17:54:45","leagueName":"premier-league","day":"Sunday,","date":"06 Mar 2022,","time":"15:00","homeTeam":"Watford","awayTeam":"Arsenal","mlFirstHalf":[{"bookMakerName":"Betclic.fr","hw":"6.45","d":"3.90","aw":"1.52"},{"bookMakerName":"bwin.fr","hw":"6.00","d":"4.00","aw":"1.49"}],"mlSecondHalf":[{"bookMakerName":"Betclic.fr","hw":"6.45","d":"3.90","aw":"1.52"},{"bookMakerName":"bwin.fr","hw":"6.00","d":"4.00","aw":"1.49"}],"mlFullTime":[{"bookMakerName":"Betclic.fr","hw":"6.45","d":"3.90","aw":"1.52"},{"bookMakerName":"bwin.fr","hw":"6.00","d":"4.00","aw":"1.49"}],"underOver25":[{"bookmakerName":"Betclic.fr","oddsOver":"1.79","oddsUnder":"1.84"},{"bookmakerName":"bwin.fr","oddsOver":"1.73","oddsUnder":"1.77"}],"underOver15":[{"bookmakerName":"Betclic.fr","oddsOver":"1.25","oddsUnder":"3.40"},{"bookmakerName":"bwin.fr","oddsOver":"1.23","oddsUnder":"3.10"}],"underOver35":[{"bookmakerName":"Betclic.fr","oddsOver":"2.90","oddsUnder":"1.32"},{"bookmakerName":"bwin.fr","oddsOver":"2.80","oddsUnder":"1.28"}]}