{"scrapedAt":"2025-12-08 18:14:01","leagueName":"premier-league","day":"Saturday,","date":"11 Dec 2021,","time":"16:00","homeTeam":"Chelsea","awayTeam":"Leeds","mlFirstHalf":[{"bookMakerName":"Betclic.fr","hw":"1.18","d":"6.00","aw":"11.80"}],"mlSecondHalf":[{"bookMakerName":"Betclic.fr","hw":"1.18","d":"6.00","aw":"11.80"}],"mlFullTime":[{"bookMakerName":"Betclic.fr","hw":"1.18","d":"6.00","aw":"11.80"}],"underOver25":[{"bookmakerName":"Betclic.fr","oddsOver":"1.40","oddsUnder":"2.58"}],"underOver15":[{"bookmakerName":"Betclic.fr","oddsOver":"1.11","oddsUnder":"5.65"}],"underOver35":[{"bookmakerName":"Betclic.fr","oddsOver":"2.01","oddsUnder":"1.66"}]}