{"scrapedAt":"2025-12-08 18:40:04","leagueName":"premier-league","day":"Saturday,","date":"15 Apr 2023,","time":"09:00","homeTeam":"Wolves","awayTeam":"Brentford","mlFirstHalf":[{"bookMakerName":"Betclic.fr","hw":"2.75","d":"3.25","aw":"2.52"},{"bookMakerName":"bwin.fr","hw":"2.65","d":"3.00","aw":"2.60"},{"bookMakerName":"Unibet.fr","hw":"2.78","d":"3.18","aw":"2.55"}],"mlSecondHalf":[{"bookMakerName":"Betclic.fr","hw":"2.75","d":"3.25","aw":"2.52"},{"bookMakerName":"bwin.fr","hw":"2.65","d":"3.00","aw":"2.60"},{"bookMakerName":"Unibet.fr","hw":"2.78","d":"3.18","aw":"2.55"}],"mlFullTime":[{"bookMakerName":"Betclic.fr","hw":"2.75","d":"3.25","aw":"2.52"},{"bookMakerName":"bwin.fr","hw":"2.65","d":"3.00","aw":"2.60"},{"bookMakerName":"Unibet.fr","hw":"2.78","d":"3.18","aw":"2.55"}],"underOver25":[{"bookmakerName":"Betclic.fr","oddsOver":"2.05","oddsUnder":"1.56"},{"bookmakerName":"bwin.fr","oddsOver":"2.00","oddsUnder":"1.55"}],"underOver15":[{"bookmakerName":"Betclic.fr","oddsOver":"1.34","oddsUnder":"2.67"},{"bookmakerName":"bwin.fr","oddsOver":"1.33","oddsUnder":"2.60"}],"underOver35":[{"bookmakerName":"Betclic.fr","oddsOver":"3.47","oddsUnder":"1.19"},{"bookmakerName":"bwin.fr","oddsOver":"3.50","oddsUnder":"1.19"}]}