{"scrapedAt":"2025-12-08 17:22:55","leagueName":"premier-league","day":"Monday,","date":"18 Jan 2021,","time":"14:00","homeTeam":"Arsenal","awayTeam":"Newcastle","mlFirstHalf":[{"bookMakerName":"Betclic.fr","hw":"1.40","d":"5.00","aw":"8.60"},{"bookMakerName":"bwin.fr","hw":"1.36","d":"4.40","aw":"7.25"},{"bookMakerName":"Unibet.fr","hw":"1.37","d":"4.95","aw":"8.50"},{"bookMakerName":"Winamax","hw":"1.44","d":"4.80","aw":"7.75"}],"mlSecondHalf":[{"bookMakerName":"Betclic.fr","hw":"1.40","d":"5.00","aw":"8.60"},{"bookMakerName":"bwin.fr","hw":"1.36","d":"4.40","aw":"7.25"},{"bookMakerName":"Unibet.fr","hw":"1.37","d":"4.95","aw":"8.50"},{"bookMakerName":"Winamax","hw":"1.44","d":"4.80","aw":"7.75"}],"mlFullTime":[{"bookMakerName":"Betclic.fr","hw":"1.40","d":"5.00","aw":"8.60"},{"bookMakerName":"bwin.fr","hw":"1.36","d":"4.40","aw":"7.25"},{"bookMakerName":"Unibet.fr","hw":"1.37","d":"4.95","aw":"8.50"},{"bookMakerName":"Winamax","hw":"1.44","d":"4.80","aw":"7.75"}],"underOver25":[{"bookmakerName":"Betclic.fr","oddsOver":"1.59","oddsUnder":"1.92"},{"bookmakerName":"bwin.fr","oddsOver":"1.57","oddsUnder":"1.95"},{"bookmakerName":"Winamax","oddsOver":"1.54","oddsUnder":"1.92"}],"underOver15":[{"bookmakerName":"Betclic.fr","oddsOver":"1.18","oddsUnder":"3.68"},{"bookmakerName":"bwin.fr","oddsOver":"1.17","oddsUnder":"3.40"},{"bookmakerName":"Winamax","oddsOver":"1.14","oddsUnder":"3.75"}],"underOver35":[{"bookmakerName":"Betclic.fr","oddsOver":"2.44","oddsUnder":"1.35"},{"bookmakerName":"bwin.fr","oddsOver":"2.40","oddsUnder":"1.36"},{"bookmakerName":"Winamax","oddsOver":"2.40","oddsUnder":"1.33"}]}