{"scrapedAt":"2025-12-08 18:32:07","leagueName":"premier-league","day":"Saturday,","date":"20 May 2023,","time":"11:30","homeTeam":"Nottingham","awayTeam":"Arsenal","mlFirstHalf":[{"bookMakerName":"Betclic.fr","hw":"5.25","d":"4.10","aw":"1.60"},{"bookMakerName":"bwin.fr","hw":"4.80","d":"3.80","aw":"1.60"},{"bookMakerName":"Unibet.fr","hw":"5.15","d":"4.20","aw":"1.59"}],"mlSecondHalf":[{"bookMakerName":"Betclic.fr","hw":"5.25","d":"4.10","aw":"1.60"},{"bookMakerName":"bwin.fr","hw":"4.80","d":"3.80","aw":"1.60"},{"bookMakerName":"Unibet.fr","hw":"5.15","d":"4.20","aw":"1.59"}],"mlFullTime":[{"bookMakerName":"Betclic.fr","hw":"5.25","d":"4.10","aw":"1.60"},{"bookMakerName":"bwin.fr","hw":"4.80","d":"3.80","aw":"1.60"},{"bookMakerName":"Unibet.fr","hw":"5.15","d":"4.20","aw":"1.59"}],"underOver25":[{"bookmakerName":"Betclic.fr","oddsOver":"1.61","oddsUnder":"1.97"},{"bookmakerName":"bwin.fr","oddsOver":"1.60","oddsUnder":"1.95"}],"underOver15":[{"bookmakerName":"Betclic.fr","oddsOver":"1.18","oddsUnder":"3.90"},{"bookmakerName":"bwin.fr","oddsOver":"1.18","oddsUnder":"3.60"}],"underOver35":[{"bookmakerName":"Betclic.fr","oddsOver":"2.48","oddsUnder":"1.38"},{"bookmakerName":"bwin.fr","oddsOver":"2.45","oddsUnder":"1.37"}]}