{"scrapedAt":"2025-12-08 20:46:00","leagueName":"premier-league","day":"Thursday,","date":"25 Apr 2024,","time":"12:00","homeTeam":"Brighton","awayTeam":"Manchester City","mlFirstHalf":[{"bookMakerName":"Betclic.fr","hw":"8.00","d":"5.75","aw":"1.30"},{"bookMakerName":"Unibet.fr","hw":"8.50","d":"6.00","aw":"1.29"}],"mlSecondHalf":[{"bookMakerName":"Betclic.fr","hw":"8.00","d":"5.75","aw":"1.30"},{"bookMakerName":"Unibet.fr","hw":"8.50","d":"6.00","aw":"1.29"}],"mlFullTime":[{"bookMakerName":"Betclic.fr","hw":"8.00","d":"5.75","aw":"1.30"},{"bookMakerName":"Unibet.fr","hw":"8.50","d":"6.00","aw":"1.29"}],"underOver25":[{"bookmakerName":"Betclic.fr","oddsOver":"1.38","oddsUnder":"2.40"},{"bookmakerName":"Unibet.fr","oddsOver":"1.35","oddsUnder":"2.34"}],"underOver15":[{"bookmakerName":"Betclic.fr","oddsOver":"1.09","oddsUnder":"5.25"},{"bookmakerName":"Unibet.fr","oddsOver":"1.09","oddsUnder":"4.90"}],"underOver35":[{"bookmakerName":"Betclic.fr","oddsOver":"1.95","oddsUnder":"1.58"},{"bookmakerName":"Unibet.fr","oddsOver":"1.89","oddsUnder":"1.56"}]}