{"scrapedAt":"2025-12-08 20:55:40","leagueName":"premier-league","day":"Wednesday,","date":"31 Jan 2024,","time":"12:15","homeTeam":"Liverpool","awayTeam":"Chelsea","mlFirstHalf":[{"bookMakerName":"Betclic.fr","hw":"1.56","d":"4.40","aw":"4.70"},{"bookMakerName":"bwin.fr","hw":"1.63","d":"4.00","aw":"4.20"},{"bookMakerName":"Unibet.fr","hw":"1.62","d":"4.45","aw":"4.85"}],"mlSecondHalf":[{"bookMakerName":"Betclic.fr","hw":"1.56","d":"4.40","aw":"4.70"},{"bookMakerName":"bwin.fr","hw":"1.63","d":"4.00","aw":"4.20"},{"bookMakerName":"Unibet.fr","hw":"1.62","d":"4.45","aw":"4.85"}],"mlFullTime":[{"bookMakerName":"Betclic.fr","hw":"1.56","d":"4.40","aw":"4.70"},{"bookMakerName":"bwin.fr","hw":"1.63","d":"4.00","aw":"4.20"},{"bookMakerName":"Unibet.fr","hw":"1.62","d":"4.45","aw":"4.85"}],"underOver25":[{"bookmakerName":"Betclic.fr","oddsOver":"1.42","oddsUnder":"2.40"},{"bookmakerName":"bwin.fr","oddsOver":"1.39","oddsUnder":"2.37"},{"bookmakerName":"Unibet.fr","oddsOver":"1.38","oddsUnder":"2.30"}],"underOver15":[{"bookmakerName":"Betclic.fr","oddsOver":"1.11","oddsUnder":"5.25"},{"bookmakerName":"bwin.fr","oddsOver":"1.11","oddsUnder":"4.60"},{"bookmakerName":"Unibet.fr","oddsOver":"1.10","oddsUnder":"4.75"}],"underOver35":[{"bookmakerName":"Betclic.fr","oddsOver":"2.05","oddsUnder":"1.60"},{"bookmakerName":"bwin.fr","oddsOver":"1.98","oddsUnder":"1.57"},{"bookmakerName":"Unibet.fr","oddsOver":"1.95","oddsUnder":"1.55"}]}